every_ai/__init__.py
every_ai/base.py
every_ai/exceptions.py
every_ai/registry.py
every_ai/backends/__init__.py
every_ai/backends/anthropic/__init__.py
every_ai/backends/anthropic/backend.py
every_ai/backends/openai/__init__.py
every_ai/backends/openai/backend.py
every_ai-1.1.1.dist-info/LICENSE
every_ai-1.1.1.dist-info/WHEEL
every_ai-1.1.1.dist-info/METADATA
every_ai-1.1.1.dist-info/RECORD
