Metadata-Version: 2.1
Name: every-ai
Version: 1.1.1
Summary: A simple wrapper around multiple LLM/AI providers
Author-email: Tom Usher <tom@tomusher.com>
Requires-Python: >=3.8
Classifier: Development Status :: 3 - Alpha
Classifier: Intended Audience :: Developers
Classifier: License :: OSI Approved :: MIT License
Classifier: Operating System :: OS Independent
Classifier: Programming Language :: Python
Classifier: Programming Language :: Python :: 3
Classifier: Programming Language :: Python :: 3.8
Classifier: Programming Language :: Python :: 3.9
Classifier: Programming Language :: Python :: 3.10
Classifier: Programming Language :: Python :: 3.11
Requires-Dist: anthropic>=0.3.11 ; extra == "anthropic"
Requires-Dist: mkdocs>=1.4.2 ; extra == "docs"
Requires-Dist: mkdocs-material>=9.1.3 ; extra == "docs"
Requires-Dist: mkdocs-awesome-pages-plugin>=2.8.0 ; extra == "docs"
Requires-Dist: openai>=1.0.0b1 ; extra == "openai"
Requires-Dist: pre-commit>=3.4.0 ; extra == "testing"
Requires-Dist: pytest>=7.2.2 ; extra == "testing"
Project-URL: Home, https://github.com/tomusher/every-ai
Provides-Extra: anthropic
Provides-Extra: docs
Provides-Extra: openai
Provides-Extra: testing
